smtp_dane_verify/__init__.py
smtp_dane_verify/__main__.py
smtp_dane_verify/api.py
smtp_dane_verify/cli.py
smtp_dane_verify/dns_records.py
smtp_dane_verify/dnssec.py
smtp_dane_verify/external_resolver.py
smtp_dane_verify/test1.py
smtp_dane_verify/verification.py
smtp_dane_verify-0.3.2.dist-info/METADATA
smtp_dane_verify-0.3.2.dist-info/WHEEL
smtp_dane_verify-0.3.2.dist-info/entry_points.txt
smtp_dane_verify-0.3.2.dist-info/licenses/LICENSE.txt
smtp_dane_verify-0.3.2.dist-info/RECORD
