Metadata-Version: 2.4
Name: smtp-dane-verify
Version: 0.3.2
Summary: A small library, command-line utility, Prometheus exporter, and JSON/HTTP/FastAPI service to check DANE/TLSA-RRs against SMTP servers.
License-File: LICENSE.txt
Classifier: License :: OSI Approved :: GNU Affero General Public License v3
Requires-Python: >=3.12
Requires-Dist: cryptography>=45.0.6
Requires-Dist: dnspython>=2.7.0
Requires-Dist: fastapi>=0.116.1
Requires-Dist: pydantic>=2.11.7
Requires-Dist: uvicorn>=0.35.0
Provides-Extra: fastapi
Requires-Dist: fastapi[standard]>=0.116.1; extra == 'fastapi'
